CHANGES.txt
LICENSE.txt
MANIFEST.in
README.rst
setup.py
IpCamPy.egg-info/PKG-INFO
IpCamPy.egg-info/SOURCES.txt
IpCamPy.egg-info/dependency_links.txt
IpCamPy.egg-info/not-zip-safe
IpCamPy.egg-info/requires.txt
IpCamPy.egg-info/top_level.txt
bin/campatrol
ipcampy/__init__.py
ipcampy/common.py
ipcampy/foscam.py
ipcampy/globals.py
ipcampy/sentry.py
ipcampy/web_panel.py
ipcampy/test/__init__.py
ipcampy/test/test_foscam.py
ipcampy/test/test_sentry.py
ipcamweb/__init__.py
ipcamweb/dashboard.py
ipcamweb/utils.py
ipcamweb/static/custom.min.css
ipcamweb/static/favicon.png
ipcamweb/static/jquery.mobile.icons.min.css
ipcamweb/static/images/ajax-loader.gif
ipcamweb/static/images/icons-png/action-black.png
ipcamweb/static/images/icons-png/action-white.png
ipcamweb/static/images/icons-png/alert-black.png
ipcamweb/static/images/icons-png/alert-white.png
ipcamweb/static/images/icons-png/arrow-d-black.png
ipcamweb/static/images/icons-png/arrow-d-l-black.png
ipcamweb/static/images/icons-png/arrow-d-l-white.png
ipcamweb/static/images/icons-png/arrow-d-r-black.png
ipcamweb/static/images/icons-png/arrow-d-r-white.png
ipcamweb/static/images/icons-png/arrow-d-white.png
ipcamweb/static/images/icons-png/arrow-l-black.png
ipcamweb/static/images/icons-png/arrow-l-white.png
ipcamweb/static/images/icons-png/arrow-r-black.png
ipcamweb/static/images/icons-png/arrow-r-white.png
ipcamweb/static/images/icons-png/arrow-u-black.png
ipcamweb/static/images/icons-png/arrow-u-l-black.png
ipcamweb/static/images/icons-png/arrow-u-l-white.png
ipcamweb/static/images/icons-png/arrow-u-r-black.png
ipcamweb/static/images/icons-png/arrow-u-r-white.png
ipcamweb/static/images/icons-png/arrow-u-white.png
ipcamweb/static/images/icons-png/audio-black.png
ipcamweb/static/images/icons-png/audio-white.png
ipcamweb/static/images/icons-png/back-black.png
ipcamweb/static/images/icons-png/back-white.png
ipcamweb/static/images/icons-png/bars-black.png
ipcamweb/static/images/icons-png/bars-white.png
ipcamweb/static/images/icons-png/bullets-black.png
ipcamweb/static/images/icons-png/bullets-white.png
ipcamweb/static/images/icons-png/calendar-black.png
ipcamweb/static/images/icons-png/calendar-white.png
