Metadata-Version: 1.1
Name: IpCamPy
Version: 0.3.0
Summary: Easily control ip cameras. Comes with built in utilities to make a simple surveillance system.
Home-page: https://github.com/eraclitux/ipcampy
Author: Andrea Masi
Author-email: eraclitux@gmail.com
License: MIT
Keywords: ipcam foscam raspberrypi surveillance
Platform: UNKNOWN
Classifier: Development Status :: 3 - Alpha
Classifier: License :: OSI Approved :: MIT License
Classifier: Programming Language :: Python :: 2.7
Classifier: Topic :: Multimedia :: Video :: Capture
